hyku_ingest/__init__.py
hyku_ingest/create_sheet/__init__.py
hyku_ingest/create_sheet/create_sheet.py
hyku_ingest/ingest.py
hyku_ingest/split_sheet/__init__.py
hyku_ingest/split_sheet/split_sheet.py
hyku_ingest-0.0.16.dist-info/METADATA
hyku_ingest-0.0.16.dist-info/WHEEL
hyku_ingest-0.0.16.dist-info/entry_points.txt
hyku_ingest-0.0.16.dist-info/RECORD
