Metadata-Version: 2.3
Name: hyku-ingest
Version: 0.0.16
Summary: 
Author: Weston49
Author-email: weston.agreda@gmail.com
Requires-Python: >=3.13,<4.0
Classifier: Programming Language :: Python :: 3
Classifier: Programming Language :: Python :: 3.13
Requires-Dist: argparse (>=1.4.0,<2.0.0)
